langchain_ampersend/__init__.py
langchain_ampersend/py.typed
langchain_ampersend/a2a/__init__.py
langchain_ampersend/a2a/toolkit.py
langchain_ampersend_ai-0.0.2.dist-info/METADATA
langchain_ampersend_ai-0.0.2.dist-info/WHEEL
langchain_ampersend_ai-0.0.2.dist-info/RECORD
