Metadata-Version: 2.4
Name: langchain-ampersend-ai
Version: 0.0.2
Summary: LangChain integration for Ampersend x402 payments
Requires-Python: >=3.13
Requires-Dist: ampersend-sdk
Requires-Dist: httpx>=0.27.0
Requires-Dist: langchain-core>=0.3.0
